.gitattributes
.gitignore
.todo
CHANGELOG.md
COLORS.html
LICENSE
MANIFEST.in
README.md
pyproject.toml
rx7/__init__.py
rx7/__main__.py
rx7/_dev.py
rx7/_developer.py
rx7/datetime.py
rx7/decorator.py
rx7/files.py
rx7/functions.py
rx7/internet.py
rx7/io.py
rx7/random.py
rx7/record.py
rx7/style.py
rx7/system.py
rx7/terminal.py
rx7.egg-info/PKG-INFO
rx7.egg-info/SOURCES.txt
rx7.egg-info/dependency_links.txt
rx7.egg-info/requires.txt
rx7.egg-info/top_level.txt