Metadata-Version: 2.1
Name: rx7
Version: 4.0.0
Summary: Useful functions and methods are all gathered in one module
Author-email: Ramin-RX7 <rawmin.rx@gmail.com>
License: LGPL
Project-URL: Homepage, https://github.com/Ramin-RX7/RX7-Lib
Project-URL: Bug Tracker, https://github.com/Ramin-RX7/RX7-Lib/issues
Project-URL: documentation, https://github.com/Ramin-RX7/RX7-Lib/wiki
Project-URL: repository, https://github.com/Ramin-RX7/RX7-Lib
Project-URL: changelog, https://github.com/Ramin-RX7/RX7-Lib/blob/master/CHANGELOG.md
Keywords: shortcut,collection
Classifier: Programming Language :: Python :: 3
Requires-Python: >=3.10
Provides-Extra: all
License-File: LICENSE
